{
    "singleConsonants" : [
        "b", 
        "d", 
        "f", 
        "g", 
        "h", 
        "j", 
        "k", 
        "l", 
        "m", 
        "n", 
        "p", 
        "r",
        "s",
        "t",
        "v",
        "w",
        "x",
        "y",
        "z"
    ],
    "doubleConsonants" : [ 
        "ch", 
        "sh", 
        "th",
        "tr",
        "kr",
        "ks",
        "ny",
        "gr",
        "gy"
    ],
    "singleVowels" : [
        "a",
        "e",
        "i",
        "o",
        "u"
    ],
    "doubleVowels" : [
        "ee",
        "ea",
        "ou",
        "io",
        "oi",
        "ua",
        "au",
        "oo",
        "ay",
        "ey",
        "oy",
        "ae",
        "ai",
        "eu",
        "eo"
    ],
    "numbers" : [
        "0",
        "1",
        "2",
        "3",
        "4",
        "5",
        "6",
        "7",
        "8",
        "9"
    ],
    "symbols" : [
        "!",
        "?",
        ".",
        "@",
        "#",
        "%",
        "^",
        "&",
        "*",
        "-",
        "+",
        "_",
        "="
    ]

}